cqlite/__init__.py
cqlite/cqlite.py
cqlite-0.2.0.dist-info/LICENSE
cqlite-0.2.0.dist-info/METADATA
cqlite-0.2.0.dist-info/WHEEL
cqlite-0.2.0.dist-info/entry_points.txt
cqlite-0.2.0.dist-info/top_level.txt
cqlite-0.2.0.dist-info/RECORD
