Metadata-Version: 2.1
Name: cqlite
Version: 0.2.0
Summary: Query a CSV file from the commandline
Author-email: Emil Kloeden <emilkloeden@gmail.com>
Project-URL: Homepage, https://github.com/emilkloeden/cqlite
Project-URL: Bug Tracker, https://github.com/emilkloeden/cqlite/issues
Classifier: Programming Language :: Python :: 3
Classifier: License :: OSI Approved :: MIT License
Classifier: Operating System :: OS Independent
Requires-Python: >=3.10
License-File: LICENSE
Requires-Dist: typer (==0.7.0)
Requires-Dist: rich (==12.6.0)
